llama_index/readers/astra_db/__init__.py
llama_index/readers/astra_db/base.py
llama_index_readers_astra_db-0.4.1.dist-info/METADATA
llama_index_readers_astra_db-0.4.1.dist-info/WHEEL
llama_index_readers_astra_db-0.4.1.dist-info/licenses/LICENSE
llama_index_readers_astra_db-0.4.1.dist-info/RECORD
