Metadata-Version: 2.4
Name: llama-index-readers-astra-db
Version: 0.4.1
Summary: llama-index readers astra_db integration
Author-email: Your Name <you@example.com>
Maintainer: erichare
License-Expression: MIT
License-File: LICENSE
Requires-Python: <4.0,>=3.9
Requires-Dist: astrapy<2,>=1
Requires-Dist: llama-index-core<0.15,>=0.13.0
